ass2srt/__init__.py
ass2srt/ass2srt.py
ass2srt-0.0.5.dist-info/LICENSE
ass2srt-0.0.5.dist-info/METADATA
ass2srt-0.0.5.dist-info/WHEEL
ass2srt-0.0.5.dist-info/entry_points.txt
ass2srt-0.0.5.dist-info/top_level.txt
ass2srt-0.0.5.dist-info/RECORD
