Metadata-Version: 2.1
Name: ass2srt
Version: 0.0.5
Summary: A tool that convert .ass subtitles to .srt
Home-page: https://github.com/zcq100/ass2srt
Author: zcq100
Author-email: zcq100@gmail.com
Classifier: Programming Language :: Python :: 3
Classifier: License :: OSI Approved :: MIT License
Classifier: Operating System :: OS Independent
Classifier: Topic :: Text Processing
Requires-Python: >=3.6
License-File: LICENSE
